{
  "industry": "gc",
  "displayName": "General Contractor",
  "demoCompanyName": "Summit General Contractors Inc",
  "demoOwnerName": "Dave Whitfield",
  "priceBookItems": [
    { "name": "2x4x8 Stud — KD Douglas Fir", "unit": "ea", "price": 5.80 },
    { "name": "2x6x8 Lumber — KD Douglas Fir", "unit": "ea", "price": 9.20 },
    { "name": "3/4\" Plywood Sheathing (sheet)", "unit": "sheet", "price": 68.00 },
    { "name": "OSB 7/16\" Sheathing (sheet)", "unit": "sheet", "price": 24.50 },
    { "name": "Ready-Mix Concrete (per yard)", "unit": "cy", "price": 165.00 },
    { "name": "Rebar #4 (per ft)", "unit": "ft", "price": 1.20 },
    { "name": "5/8\" Drywall (sheet)", "unit": "sheet", "price": 18.50 },
    { "name": "1/2\" Drywall (sheet)", "unit": "sheet", "price": 14.75 },
    { "name": "Joint Compound — 5-Gallon Bucket", "unit": "ea", "price": 22.00 },
    { "name": "Fiberglass Batt Insulation R-19 (per sqft)", "unit": "sqft", "price": 1.05 },
    { "name": "Asphalt Shingle — 30-Year (per sq)", "unit": "sq", "price": 115.00 },
    { "name": "Roofing Felt 30# (roll)", "unit": "roll", "price": 45.00 },
    { "name": "Ice & Water Shield (roll)", "unit": "roll", "price": 95.00 },
    { "name": "Exterior Paint — 5 Gallon", "unit": "ea", "price": 185.00 },
    { "name": "Interior Paint — 5 Gallon", "unit": "ea", "price": 145.00 },
    { "name": "3.5\" Framing Nails — 5 lb Box", "unit": "box", "price": 28.00 },
    { "name": "Concrete Anchor Bolts 1/2\"x7\" (box)", "unit": "box", "price": 42.00 },
    { "name": "Window — Double Hung Vinyl 3x4", "unit": "ea", "price": 285.00 },
    { "name": "Exterior Door — Steel 3068 Pre-Hung", "unit": "ea", "price": 425.00 },
    { "name": "Interior Door — Hollow Core 2868", "unit": "ea", "price": 95.00 },
    { "name": "Carpet — Standard Grade (per sqyd)", "unit": "sqyd", "price": 28.00 },
    { "name": "Tile — Ceramic Floor 12x12 (per sqft)", "unit": "sqft", "price": 3.50 },
    { "name": "Hardwood Flooring — Engineered (per sqft)", "unit": "sqft", "price": 7.25 },
    { "name": "Electrical Subcontractor (per hr)", "unit": "hr", "price": 145.00 },
    { "name": "Plumbing Subcontractor (per hr)", "unit": "hr", "price": 125.00 },
    { "name": "HVAC Subcontractor (per hr)", "unit": "hr", "price": 135.00 },
    { "name": "General Labor (per hr)", "unit": "hr", "price": 65.00 },
    { "name": "Foreman Labor (per hr)", "unit": "hr", "price": 95.00 },
    { "name": "Equipment Rental — Excavator (per day)", "unit": "day", "price": 850.00 },
    { "name": "Dumpster Rental (per haul)", "unit": "ea", "price": 475.00 }
  ],
  "projectPhases": [
    { "id": "pre-construction", "label": "Pre-Construction", "order": 1 },
    { "id": "foundation", "label": "Foundation", "order": 2 },
    { "id": "framing", "label": "Framing", "order": 3 },
    { "id": "mep-rough", "label": "MEP Rough", "order": 4 },
    { "id": "drywall", "label": "Drywall", "order": 5 },
    { "id": "finish", "label": "Finish", "order": 6 },
    { "id": "closeout", "label": "Closeout", "order": 7 }
  ],
  "labelOverrides": {
    "invoice": "Draw Request",
    "estimate": "Bid",
    "project": "Project",
    "crew": "Subcontractors"
  },
  "visiblePanels": [
    "home",
    "projects",
    "estimate",
    "field-logs",
    "price-book",
    "collections",
    "blueprints",
    "nexus"
  ],
  "ohmReference": "IBC",
  "nexusPersonality": "I'm NEXUS, your general contracting operations assistant — I track draw schedules, subcontractor milestones, and IBC compliance so your projects stay on budget and on time. Tell me about your project and I'll help you stay ahead of every phase."
}
